{
  "name": "Charybdis Mini",
  "vendorProductId": 2834831412,
  "macros": [
    "{+KC_ENT}{10}{-KC_ENT}{85}r{10}{+KC_ENT}{10}{-KC_ENT}",
    "{+KC_ENT}{10}{-KC_ENT}{85}Wait{10}{+KC_ENT}{10}{-KC_ENT}",
    "{+KC_ENT}{10}{-KC_ENT}{85}gg{10}{+KC_ENT}{10}{-KC_ENT}",
    "{+KC_ENT}{10}{-KC_ENT}{85}Need more ammo{10}{+KC_ENT}{10}{-KC_ENT}",
    "{+KC_ENT}{10}{-KC_ENT}{85}Sorry!{10}{+KC_ENT}{10}{-KC_ENT}",
    "{+KC_ENT}{10}{-KC_ENT}{85}> Here <{10}{+KC_ENT}{10}{-KC_ENT}",
    "{+KC_ENT}{10}{-KC_ENT}{85}> Right{10}{+KC_ENT}{10}{-KC_ENT}",
    "{+KC_ENT}{10}{-KC_ENT}{85}< Left{10}{+KC_ENT}{10}{-KC_ENT}",
    "{+KC_ENT}{10}{-KC_ENT}{85}Yes{10}{+KC_ENT}{10}{-KC_ENT}",
    "{+KC_ENT}{10}{-KC_ENT}{85}No{10}{+KC_ENT}{10}{-KC_ENT}",
    "{+KC_ENT}{10}{-KC_ENT}{85}I chat with macros and can't reply, sorry!{10}{+KC_ENT}{10}{-KC_ENT}",
    "{+KC_ENT}{10}{-KC_ENT}{85}Thanks!{10}{+KC_ENT}{10}{-KC_ENT}",
    "{+KC_ENT}{10}{-KC_ENT}{85}May I take extra?{10}{+KC_ENT}{10}{-KC_ENT}",
    "{+KC_ENT}{10}{-KC_ENT}{85}AFK{10}{+KC_ENT}{10}{-KC_ENT}",
    "{+KC_ENT}{10}{-KC_ENT}{85}I'm back{10}{+KC_ENT}{10}{-KC_ENT}",
    "{+KC_ENT}{10}{-KC_ENT}{85}I need help!{10}{+KC_ENT}{10}{-KC_ENT}"
  ],
  "layers": [
    [
      "KC_TAB",
      "KC_Q",
      "KC_W",
      "KC_E",
      "KC_R",
      "KC_T",
      "KC_CAPS",
      "KC_A",
      "KC_S",
      "KC_D",
      "KC_F",
      "KC_G",
      "KC_LSFT",
      "KC_Z",
      "KC_X",
      "KC_C",
      "KC_V",
      "KC_B",
      "KC_NO",
      "KC_SPC",
      "KC_NO",
      "KC_LGUI",
      "KC_LALT",
      "KC_NO",
      "KC_BSPC",
      "KC_P",
      "KC_O",
      "KC_I",
      "KC_U",
      "KC_Y",
      "KC_ENT",
      "KC_SCLN",
      "KC_L",
      "KC_K",
      "KC_J",
      "KC_H",
      "KC_ESC",
      "KC_SLSH",
      "KC_DOT",
      "KC_COMM",
      "KC_M",
      "KC_N",
      "KC_NO",
      "FN_MO23",
      "KC_NO",
      "FN_MO13",
      "KC_NO",
      "KC_NO"
    ],
    [
      "S(KC_GRV)",
      "S(KC_7)",
      "S(KC_8)",
      "S(KC_9)",
      "S(KC_0)",
      "KC_PPLS",
      "KC_GRV",
      "S(KC_4)",
      "S(KC_5)",
      "S(KC_6)",
      "S(KC_QUOT)",
      "S(KC_LBRC)",
      "KC_LSFT",
      "S(KC_1)",
      "S(KC_2)",
      "S(KC_3)",
      "S(KC_BSLS)",
      "S(KC_RBRC)",
      "KC_NO",
      "KC_MS_BTN2",
      "KC_NO",
      "KC_MS_BTN1",
      "KC_MS_BTN3",
      "KC_NO",
      "KC_DEL",
      "KC_0",
      "KC_9",
      "KC_8",
      "KC_7",
      "KC_EQL",
      "KC_LBRC",
      "KC_QUOT",
      "KC_6",
      "KC_5",
      "KC_4",
      "KC_MINS",
      "KC_RBRC",
      "KC_BSLS",
      "KC_3",
      "KC_2",
      "KC_1",
      "S(KC_MINS)",
      "KC_NO",
      "DF(0)",
      "KC_NO",
      "MO(3)",
      "KC_NO",
      "KC_NO"
    ],
    [
      "KC_TAB",
      "KC_T",
      "KC_Q",
      "KC_W",
      "KC_E",
      "KC_V",
      "KC_CAPS",
      "KC_R",
      "KC_A",
      "KC_S",
      "KC_D",
      "KC_F",
      "KC_LALT",
      "KC_J",
      "KC_Z",
      "KC_C",
      "KC_X",
      "KC_M",
      "KC_NO",
      "KC_SPC",
      "KC_NO",
      "KC_G",
      "KC_LSFT",
      "KC_NO",
      "KC_MNXT",
      "KC_F10",
      "KC_F9",
      "KC_F8",
      "KC_F7",
      "KC_VOLU",
      "KC_MPRV",
      "KC_F11",
      "KC_F6",
      "KC_F5",
      "KC_F4",
      "KC_VOLD",
      "KC_MPLY",
      "KC_F12",
      "KC_F3",
      "KC_F2",
      "KC_F1",
      "KC_MUTE",
      "KC_NO",
      "DF(0)",
      "KC_NO",
      "MO(3)",
      "KC_NO",
      "KC_NO"
    ],
    [
      "KC_NO",
      "MACRO(15)",
      "MACRO(9)",
      "MACRO(0)",
      "MACRO(8)",
      "MACRO(3)",
      "KC_NO",
      "MACRO(12)",
      "MACRO(7)",
      "MACRO(1)",
      "MACRO(6)",
      "MACRO(2)",
      "MACRO(13)",
      "MACRO(14)",
      "MACRO(4)",
      "MACRO(5)",
      "MACRO(11)",
      "MACRO(10)",
      "KC_NO",
      "KC_NO",
      "KC_NO",
      "KC_NO",
      "KC_NO",
      "KC_NO",
      "CUSTOM(0)",
      "RGB_VAI",
      "KC_END",
      "KC_PGUP",
      "KC_PGDN",
      "KC_HOME",
      "CUSTOM(1)",
      "RGB_VAD",
      "KC_RGHT",
      "KC_UP",
      "KC_DOWN",
      "KC_LEFT",
      "CUSTOM(6)",
      "BL_BRTG",
      "DF(3)",
      "DF(2)",
      "DF(1)",
      "DF(0)",
      "KC_NO",
      "DF(0)",
      "KC_NO",
      "KC_NO",
      "KC_NO",
      "KC_NO"
    ]
  ],
  "encoders": []
}